setup.py
clip4/__main__.py
clip4/main.py
clip4.egg-info/PKG-INFO
clip4.egg-info/SOURCES.txt
clip4.egg-info/dependency_links.txt
clip4.egg-info/entry_points.txt
clip4.egg-info/not-zip-safe
clip4.egg-info/requires.txt
clip4.egg-info/top_level.txt