Metadata-Version: 1.0
Name: clip4
Version: 0.1.0
Summary: A clipboard command line program shared with Dropbox
Home-page: https://github.com/yumaokao/clip4
Author: yumaokao
Author-email: ymkq9h@gmail.com
License: MIT
Platform: UNKNOWN
